ipynb_converter/__init__.py
ipynb_converter/ipynb_converter.py
ipynb_conversor-0.0.3.dist-info/LICENSE.txt
ipynb_conversor-0.0.3.dist-info/METADATA
ipynb_conversor-0.0.3.dist-info/WHEEL
ipynb_conversor-0.0.3.dist-info/top_level.txt
ipynb_conversor-0.0.3.dist-info/RECORD
