Metadata-Version: 2.1
Name: ipynb-conversor
Version: 0.0.3
Summary: A package for getting python code from jupyter notebook.
Home-page: https://github.com/vitia-fritelle/ipynb_converter
Author: Vitia Fritelle (Vitor Guilherme Coutinho de Barros Junior)
Author-email: <vitorjunior448@gmail.com>
License: MIT
Keywords: python,jupyter notebook,converter
Platform: UNKNOWN
Classifier: Development Status :: 3 - Alpha
Classifier: Intended Audience :: Developers
Classifier: Framework :: Jupyter
Classifier: Programming Language :: Python :: 3
Classifier: Operating System :: Unix
Classifier: Operating System :: MacOS :: MacOS X
Classifier: Operating System :: Microsoft :: Windows
License-File: LICENSE.txt
Requires-Dist: typing
